clamda.py
clamda-0.0.25.dist-info/LICENSE
clamda-0.0.25.dist-info/METADATA
clamda-0.0.25.dist-info/WHEEL
clamda-0.0.25.dist-info/entry_points.txt
clamda-0.0.25.dist-info/top_level.txt
clamda-0.0.25.dist-info/RECORD
