Metadata-Version: 2.1
Name: clamda
Version: 0.0.25
Summary: Work seamlessly with AWS Lambda Jobs
Home-page: https://github.com/haydenth/clamda
Author: Tom Hayden
Author-email: thayden@gmail.com
License: MIT
Platform: UNKNOWN
Classifier: License :: OSI Approved :: MIT License
Classifier: Operating System :: OS Independent
Classifier: Programming Language :: Python
Requires-Python: >=3.6
